{
	"info": {
		"name": "Sample API Collection",
		"_postman_id": "1234-abcd-5678-efgh",
		"description": "Collection for Sample API",
		"schema": "https://schema.getpostman.com/json/collection/v2.1.0/collection.json"
	},
	"item": [
		{
			"name": "Get Books",
			"request": {
				"method": "GET",
				"header": [],
				"url": "https://api.example.com/books"
			}
		},
		{
			"name": "Add Book",
			"request": {
				"method": "POST",
				"header": [
					{
						"key": "Content-Type",
						"value": "application/json"
					}
				],
				"body": {
					"mode": "raw",
					"raw": "{\"title\":\"New Book\",\"author\":\"Author Name\"}"
				},
				"url": "https://api.example.com/books"
			}
		}
	],
	"Transform": "AWS::Serverless-2016-10-31",
	"Resources": {
		"Api": {
			"Type": "AWS::Serverless::Api",
			"Properties": {
				"Name": {
					"Fn::Sub": [
						"${ResourceName} From Stack ${AWS::StackName}",
						{
							"ResourceName": "Api"
						}
					]
				},
				"StageName": "Prod",
				"DefinitionBody": {
					"openapi": "3.0",
					"info": {},
					"paths": {
						"/": {
							"get": {
								"responses": {}
							}
						}
					}
				},
				"EndpointConfiguration": "REGIONAL",
				"TracingEnabled": true
			}
		}
	}
}